zato_websocket_client-1.6.1-py3.4-nspkg.pth
zato/websocket/__init__.py
zato/websocket/client.py
zato_websocket_client-1.6.1.dist-info/DESCRIPTION.rst
zato_websocket_client-1.6.1.dist-info/METADATA
zato_websocket_client-1.6.1.dist-info/RECORD
zato_websocket_client-1.6.1.dist-info/WHEEL
zato_websocket_client-1.6.1.dist-info/metadata.json
zato_websocket_client-1.6.1.dist-info/namespace_packages.txt
zato_websocket_client-1.6.1.dist-info/top_level.txt
