Metadata-Version: 2.0
Name: zato-websocket-client
Version: 1.6.1
Summary: A convenience WebSocket Python client for Zato services
Home-page: https://zato.io/docs
Author: Zato Source s.r.o.
Author-email: info@zato.io
License: GNU Lesser General Public License v3 (LGPLv3)
Platform: OS Independent
Classifier: Development Status :: 5 - Production/Stable
Classifier: Environment :: Console
Classifier: Environment :: Web Environment
Classifier: Intended Audience :: Developers
Classifier: Intended Audience :: Information Technology
Classifier: Intended Audience :: Other Audience
Classifier: License :: OSI Approved :: GNU Lesser General Public License v3 (LGPLv3)
Classifier: Natural Language :: English
Classifier: Operating System :: OS Independent
Classifier: Programming Language :: Python
Classifier: Programming Language :: Python :: 2
Classifier: Programming Language :: Python :: 3
Classifier: Intended Audience :: Developers
Classifier: Topic :: Communications
Classifier: Topic :: Education :: Testing
Classifier: Topic :: Internet
Classifier: Topic :: Internet :: Proxy Servers
Classifier: Topic :: Internet :: WWW/HTTP
Classifier: Topic :: Security
Classifier: Topic :: System :: Networking
Classifier: Topic :: Utilities
Requires-Dist: future
Requires-Dist: gevent
Requires-Dist: six
Requires-Dist: ws4py
